tf_templates/__init__.py
tf_templates/client.py
tf_templates/logger_ui.py
tf_templates/resources/CV/Bounding_Box/deformable_conv_detr.py
tf_templates/resources/CV/Bounding_Box/finetune-yolo-custom-training-loop copy.ipynb
tf_templates/resources/CV/Bounding_Box/finetune-yolo-custom-training-loop.ipynb
tf_templates/resources/CV/Bounding_Box/finetune_yolo.py
tf_templates/resources/CV/Bounding_Box/hf_detr_finetune.ipynb
tf_templates/resources/CV/Bounding_Box/hf_finetune_detr.py
tf_templates/resources/CV/Bounding_Box/my-own-detr-attempt.ipynb
tf_templates/resources/CV/CV_Misc/composer_transforms.py
tf_templates/resources/CV/CV_Misc/conv_mixer.py
tf_templates/resources/CV/CV_Misc/resnet.py
tf_templates/resources/CV/CV_Misc/squeeze_and_excite_conv.py
tf_templates/resources/CV/CV_Misc/transforms_and_preprocessing.py
tf_templates/resources/CV/CV_Misc/vanilla_vit.py
tf_templates/resources/CV/CV_Misc/vit_pytorch_models.py
tf_templates/resources/CV/Image_Classification/resnet_vit_convmixer.ipynb
tf_templates/resources/CV/Image_Gen/Compute_FID.py
tf_templates/resources/CV/Image_Gen/WGAN_GP.py
tf_templates/resources/CV/Image_Gen/flow-matching.ipynb
tf_templates/resources/CV/Image_Gen/flow_matching.py
tf_templates/resources/CV/Image_Gen/gans-for-image-generation.ipynb
tf_templates/resources/CV/Image_Gen/vae-for-image-generation.ipynb
tf_templates/resources/ML/Docs/catboost_classifier_docs.txt
tf_templates/resources/ML/Docs/xgboost_classifier_docs.txt
tf_templates/resources/ML/Docs/xgboost_reg_docs.txt
tf_templates/resources/ML/ML_Misc/cuml_sklearn_hack.py
tf_templates/resources/ML/Tabular/autogluon_stuff.py
tf_templates/resources/ML/Tabular/raytune_stuff.py
tf_templates/resources/ML/Tabular/tabnet_stuff.py
tf_templates/resources/ML/Tabular/tsai-notebook.ipynb
tf_templates/resources/ML/Tabular/xgboost_stuff.py
tf_templates/resources/ML/Time_Series/patch_tst_hf.py
tf_templates/resources/ML/Time_Series/sktime_arima.py
tf_templates/resources/ML/Time_Series/sktime_inception_time.py
tf_templates-0.40.dist-info/METADATA
tf_templates-0.40.dist-info/WHEEL
tf_templates-0.40.dist-info/top_level.txt
tf_templates-0.40.dist-info/RECORD
