Metadata-Version: 2.4
Name: tf_templates
Version: 0.40
Summary: Notebook runtime diagnostics logger
Home-page: https://github.com/aitestpackage/tf-templates/new/main
Author: YourName
Classifier: Programming Language :: Python :: 3
Classifier: Framework :: Jupyter
Classifier: Intended Audience :: Developers
Requires-Dist: requests
Dynamic: author
Dynamic: classifier
Dynamic: description
Dynamic: description-content-type
Dynamic: home-page
Dynamic: requires-dist
Dynamic: summary
